LICENSE.rst
README.rst
__version__.py
setup.cfg
setup.py
vping/__init__.py
vping/__main__.py
vping/__version__.py
vping/vping.py
vping.egg-info/PKG-INFO
vping.egg-info/SOURCES.txt
vping.egg-info/dependency_links.txt
vping.egg-info/entry_points.txt
vping.egg-info/top_level.txt